fseutil/__init__.py
fseutil/__key__.py
fseutil/cli/__init__.py
fseutil/cli/__main__.py
fseutil/etc/geo.py
fseutil/etc/images_base64.py
fseutil/etc/util.py
fseutil/gui/__init__.py
fseutil/gui/__main__.py
fseutil/gui/layout/__init__.py
fseutil/gui/layout/dialog_0101_adb_datasheet_1.py
fseutil/gui/layout/dialog_0103_merging_flow.py
fseutil/gui/layout/dialog_0111_heat_detector_activation.py
fseutil/gui/layout/dialog_0401_br187_parallel_simple.py
fseutil/gui/layout/dialog_0403_br187_parallel_complex.py
fseutil/gui/layout/dialog_0405_thermal_radiation_extreme.py
fseutil/gui/layout/dialog_0601_naming_convention.py
fseutil/gui/layout/dialog_0602_pd_7974_flame_height.py
fseutil/gui/layout/main.py
fseutil/gui/layout/ui2py.py
fseutil/gui/logic/__init__.py
fseutil/gui/logic/common.py
fseutil/gui/logic/dialog_0001_pass_code.py
fseutil/gui/logic/dialog_0002_tableview.py
fseutil/gui/logic/dialog_0101_adb_datasheet_1.py
fseutil/gui/logic/dialog_0102_bs9999_datasheet_1.py
fseutil/gui/logic/dialog_0103_bs9999_merging_flow.py
fseutil/gui/logic/dialog_0111_pd7974_heat_detector_activation.py
fseutil/gui/logic/dialog_0401_br187_parallel_simple.py
fseutil/gui/logic/dialog_0402_br187_perpendicular_simple.py
fseutil/gui/logic/dialog_0403_br187_parallel_complex.py
fseutil/gui/logic/dialog_0404_br187_perpendicular_complex.py
fseutil/gui/logic/dialog_0405_thermal_radiation_extreme.py
fseutil/gui/logic/dialog_0601_naming_convention.py
fseutil/gui/logic/dialog_0602_pd7974_flame_height.py
fseutil/gui/logic/main.py
fseutil/lib/__init__.py
fseutil/lib/fse_activation_hd.py
fseutil/lib/fse_flame_height.py
fseutil/lib/fse_thermal_radiation.py
fseutil/lib/fse_thermal_radiation_3d.py
fseutil/libstd/__init__.py
fseutil/libstd/bre_br_187_2014.py
fseutil/libstd/bs_9999_2017.py
fseutil/libstd/pd_7974_1_2019.py
fseutil-0.0.0.dev20200219.dist-info/LICENSE
fseutil-0.0.0.dev20200219.dist-info/METADATA
fseutil-0.0.0.dev20200219.dist-info/WHEEL
fseutil-0.0.0.dev20200219.dist-info/entry_points.txt
fseutil-0.0.0.dev20200219.dist-info/top_level.txt
fseutil-0.0.0.dev20200219.dist-info/RECORD
