Metadata-Version: 2.1
Name: fseutil
Version: 0.0.0.dev20200219
Summary: Fire Safety Engineering Utility Tools
Home-page: https://github.com/fsepy/fseutil
Author: Ian Fu
Author-email: fuyans@gmail.com
License: UNKNOWN
Download-URL: https://github.com/fsepy/fseutil/archive/master.zip
Keywords: fire,safety,engineering
Platform: UNKNOWN
Classifier: Programming Language :: Python :: 3
Classifier: Development Status :: 4 - Beta
Classifier: Environment :: Other Environment
Classifier: Intended Audience :: Developers
Classifier: License :: OSI Approved :: Apache Software License
Classifier: Operating System :: OS Independent
Classifier: Topic :: Scientific/Engineering
Requires-Dist: pyside2 (>=5.14.1)
Requires-Dist: numpy (>=1.18.1)
Requires-Dist: docopt (>=0.6.2)
